geoscilabs/__init__.py
geoscilabs/base.py
geoscilabs/dcip/CondUtils.py
geoscilabs/dcip/DCIP_overburden_PseudoSection.py
geoscilabs/dcip/DCLayers.py
geoscilabs/dcip/DCWidgetPlate2_5D.py
geoscilabs/dcip/DCWidgetPlate_2D.py
geoscilabs/dcip/DCWidgetResLayer2D.py
geoscilabs/dcip/DCWidgetResLayer2_5D.py
geoscilabs/dcip/DCWidget_Overburden_2_5D.py
geoscilabs/dcip/DC_Pseudosections.py
geoscilabs/dcip/DC_cylinder.py
geoscilabs/dcip/DCsphere.py
geoscilabs/dcip/FreqtoTime.py
geoscilabs/dcip/__init__.py
geoscilabs/dcip/sphereElectrostatic_example.py
geoscilabs/em/BiotSavart.py
geoscilabs/em/DipoleWidget1D.py
geoscilabs/em/DipoleWidgetFD.py
geoscilabs/em/DipoleWidgetTD.py
geoscilabs/em/EMcircuit.py
geoscilabs/em/FDEM3loop.py
geoscilabs/em/FDEMDipolarfields.py
geoscilabs/em/FDEMPlanewave.py
geoscilabs/em/FDEMpipe.py
geoscilabs/em/HarmonicVMDCylWidget.py
geoscilabs/em/InductionLoop.py
geoscilabs/em/InductionSphereFEM.py
geoscilabs/em/InductionSphereTEM.py
geoscilabs/em/Loop.py
geoscilabs/em/MT.py
geoscilabs/em/MarineCSEM1D.py
geoscilabs/em/PlanewaveWidgetFD.py
geoscilabs/em/PlanewaveWidgetTD.py
geoscilabs/em/Reflection.py
geoscilabs/em/ResponseFct.py
geoscilabs/em/TDEMDipolarfields.py
geoscilabs/em/TDEMGroundedSource.py
geoscilabs/em/TDEMHorizontalLoopCylWidget.py
geoscilabs/em/TDEMInductiveSource.py
geoscilabs/em/TDEMPlanewave.py
geoscilabs/em/UXO_TEM_Widget.py
geoscilabs/em/VolumeWidget.py
geoscilabs/em/VolumeWidgetPlane.py
geoscilabs/em/__init__.py
geoscilabs/em/view.py
geoscilabs/gpr/Attenuation.py
geoscilabs/gpr/GPR_zero_offset.py
geoscilabs/gpr/GPRlab1.py
geoscilabs/gpr/Wiggle.py
geoscilabs/gpr/__init__.py
geoscilabs/gravity/__init__.py
geoscilabs/gravity/gravityDike.py
geoscilabs/gravity/gravitySphere.py
geoscilabs/inversion/LinearInversion.py
geoscilabs/inversion/LinearInversionCG.py
geoscilabs/inversion/LinearInversionDirect.py
geoscilabs/inversion/TomographyInversion.py
geoscilabs/inversion/__init__.py
geoscilabs/mag/Mag.py
geoscilabs/mag/MagDipole.py
geoscilabs-0.2.5.dist-info/LICENSE
geoscilabs-0.2.5.dist-info/METADATA
geoscilabs-0.2.5.dist-info/WHEEL
geoscilabs-0.2.5.dist-info/top_level.txt
geoscilabs-0.2.5.dist-info/RECORD
