Metadata-Version: 2.1
Name: geoscilabs
Version: 0.2.5
Summary: geoscilabs
Home-page: https://geosci.xyz
Author: GeoSci Developers
Author-email: lindseyheagy@gmail.com
License: MIT License
Download-URL: https://github.com/geoscixyz/geosci-labs
Keywords: geophysics,electromagnetics
Platform: Windows
Platform: Linux
Platform: Solaris
Platform: Mac OS-X
Platform: Unix
Classifier: Development Status :: 4 - Beta
Classifier: Intended Audience :: Education
Classifier: Intended Audience :: Science/Research
Classifier: License :: OSI Approved :: MIT License
Classifier: Programming Language :: Python
Classifier: Topic :: Scientific/Engineering
Classifier: Topic :: Scientific/Engineering :: Mathematics
Classifier: Topic :: Scientific/Engineering :: Physics
Classifier: Operating System :: Microsoft :: Windows
Classifier: Operating System :: POSIX
Classifier: Operating System :: Unix
Classifier: Operating System :: MacOS
Classifier: Natural Language :: English
Requires-Dist: numpy (>=1.7)
Requires-Dist: scipy (>=1.0)
Requires-Dist: matplotlib (>2.1)
Requires-Dist: ipywidgets
Requires-Dist: SimPEG (>=0.14.1)
Requires-Dist: discretize (>=0.4.14)
Requires-Dist: empymod (>=2.0.0)
Requires-Dist: jupyter
Requires-Dist: deepdish
Requires-Dist: Pillow
Requires-Dist: requests
Requires-Dist: cvxopt
